<Properties>
  <MonoDevelop.Ide.Workbench ActiveDocument="Abilities/CompProperties_LongDistanceTeleport.cs">
    <Files>
      <File FileName="Genes/Gene_SkillChanging.cs" Line="87" Column="39" />
      <File FileName="EBSGExtension.cs" Line="13" Column="43" />
      <File FileName="Genes/SkillChange.cs" Line="9" Column="33" />
      <File FileName="StatPart_FertilityByGenes.cs" Line="1" Column="1" />
      <File FileName="HarmonyPatches.cs" Line="268" Column="69" />
      <File FileName="Abilities/CompAbilityEffect_LongDistanceTeleport.cs" Line="77" Column="90" />
      <File FileName="EBSGUtilities.cs" Line="212" Column="10" />
      <File FileName="Abilities/CompProperties_LongDistanceTeleport.cs" Line="32" Column="6" />
    </Files>
    <Pads>
      <Pad Id="ProjectPad">
        <State name="__root__">
          <Node name="EBSGFramework" expanded="True">
            <Node name="EBSGFramework" expanded="True">
              <Node name="Abilities" expanded="True">
                <Node name="CompProperties_LongDistanceTeleport.cs" selected="True" />
              </Node>
            </Node>
          </Node>
        </State>
      </Pad>
    </Pads>
  </MonoDevelop.Ide.Workbench>
  <MonoDevelop.Ide.DebuggingService.PinnedWatches />
  <MonoDevelop.Ide.Workspace ActiveConfiguration="Debug" />
  <MonoDevelop.Ide.DebuggingService.Breakpoints>
    <BreakpointStore />
  </MonoDevelop.Ide.DebuggingService.Breakpoints>
  <MultiItemStartupConfigurations />
</Properties>